promethium/__init__.py
promethium/benchmark.py
promethium/py.typed
promethium/api/__init__.py
promethium/api/main.py
promethium/api/schemas.py
promethium/api/routers/datasets.py
promethium/api/routers/jobs.py
promethium/api/routers/ml.py
promethium/core/__init__.py
promethium/core/config.py
promethium/core/database.py
promethium/core/exceptions.py
promethium/core/io.py
promethium/core/logging.py
promethium/core/models.py
promethium/core/schemas.py
promethium/evaluation/__init__.py
promethium/evaluation/metrics.py
promethium/io/__init__.py
promethium/io/cloud.py
promethium/io/formats.py
promethium/io/readers.py
promethium/io/writers.py
promethium/io/zarr_wrapper.py
promethium/ml/__init__.py
promethium/ml/benchmark.py
promethium/ml/data.py
promethium/ml/inference.py
promethium/ml/loss.py
promethium/ml/metrics.py
promethium/ml/models_legacy.py
promethium/ml/pinns.py
promethium/ml/train.py
promethium/ml/training.py
promethium/ml/training_distributed.py
promethium/ml/data/dataset.py
promethium/ml/models/autoencoder.py
promethium/ml/models/base.py
promethium/ml/models/registry.py
promethium/ml/models/unet.py
promethium/pipelines/__init__.py
promethium/pipelines/recovery.py
promethium/signal/__init__.py
promethium/signal/deconvolution.py
promethium/signal/filters.py
promethium/signal/transforms.py
promethium/signal/reconstruction/__init__.py
promethium/signal/reconstruction/base.py
promethium/signal/reconstruction/compressive_sensing.py
promethium/signal/reconstruction/matrix_completion.py
promethium/utils/__init__.py
promethium/utils/reproducibility.py
promethium/utils/synthetic.py
promethium/utils/visualization.py
promethium/workflows/__init__.py
promethium/workflows/tasks.py
promethium_seismic-1.0.4.dist-info/licenses/LICENSE
promethium_seismic-1.0.4.dist-info/METADATA
promethium_seismic-1.0.4.dist-info/WHEEL
promethium_seismic-1.0.4.dist-info/top_level.txt
promethium_seismic-1.0.4.dist-info/RECORD
