Metadata-Version: 2.4
Name: promethium-seismic
Version: 1.0.4
Summary: Promethium - Advanced Seismic Data Recovery and Reconstruction Framework. State-of-the-art AI-driven framework for seismic signal reconstruction, denoising, and geophysical data enhancement.
Author-email: Olaf Yunus Laitinen Imanov <contact@promethium.dev>
License: CC-BY-NC-4.0
Project-URL: Homepage, https://github.com/olaflaitinen/Promethium
Project-URL: Documentation, https://github.com/olaflaitinen/Promethium#readme
Project-URL: Repository, https://github.com/olaflaitinen/Promethium
Project-URL: Issues, https://github.com/olaflaitinen/Promethium/issues
Project-URL: Changelog, https://github.com/olaflaitinen/Promethium/blob/main/CHANGELOG.md
Keywords: seismic,geophysics,reconstruction,deep-learning,signal-processing,pytorch,machine-learning,earthquake,seismic-data,denoising,data-recovery
Classifier: Development Status :: 4 - Beta
Classifier: Intended Audience :: Science/Research
Classifier: Intended Audience :: Developers
Classifier: Topic :: Scientific/Engineering :: Physics
Classifier: Topic :: Scientific/Engineering :: Artificial Intelligence
Classifier: Topic :: Scientific/Engineering :: Information Analysis
Classifier: Programming Language :: Python :: 3
Classifier: Programming Language :: Python :: 3.10
Classifier: Programming Language :: Python :: 3.11
Classifier: Programming Language :: Python :: 3.12
Classifier: License :: Other/Proprietary License
Classifier: Operating System :: OS Independent
Classifier: Typing :: Typed
Requires-Python: >=3.10
License-File: LICENSE
Requires-Dist: numpy>=1.24
Requires-Dist: scipy>=1.10
Requires-Dist: pandas>=2.0
Requires-Dist: xarray>=2023.0
Requires-Dist: obspy>=1.4.0
Requires-Dist: segyio>=1.9.0
Requires-Dist: torch>=2.0.0
Requires-Dist: scikit-learn>=1.2.0
Requires-Dist: pyyaml>=6.0
Requires-Dist: tqdm>=4.65.0
Requires-Dist: zarr>=2.12.0
Requires-Dist: PyWavelets>=1.4.0
Requires-Dist: requests>=2.25.0
Provides-Extra: server
Requires-Dist: fastapi>=0.110.0; extra == "server"
Requires-Dist: uvicorn[standard]>=0.22.0; extra == "server"
Requires-Dist: pydantic>=2.0; extra == "server"
Requires-Dist: pydantic-settings>=2.0; extra == "server"
Requires-Dist: sqlalchemy>=2.0; extra == "server"
Requires-Dist: aiosqlite>=0.19.0; extra == "server"
Requires-Dist: asyncpg>=0.29.0; extra == "server"
Requires-Dist: celery>=5.3.0; extra == "server"
Requires-Dist: redis>=4.6.0; extra == "server"
Requires-Dist: python-multipart>=0.0.6; extra == "server"
Requires-Dist: typer>=0.9.0; extra == "server"
Provides-Extra: dev
Requires-Dist: pytest>=7.0; extra == "dev"
Requires-Dist: pytest-cov>=4.0; extra == "dev"
Requires-Dist: black>=23.0; extra == "dev"
Requires-Dist: ruff>=0.0.270; extra == "dev"
Requires-Dist: mypy>=1.3.0; extra == "dev"
Requires-Dist: httpx>=0.24.0; extra == "dev"
Requires-Dist: build>=1.0.0; extra == "dev"
Requires-Dist: twine>=4.0.0; extra == "dev"
Provides-Extra: viz
Requires-Dist: matplotlib>=3.7.0; extra == "viz"
Requires-Dist: seaborn>=0.12.0; extra == "viz"
Provides-Extra: all
Requires-Dist: promethium[dev,server,viz]; extra == "all"
Dynamic: license-file
